spukhafte/__init__.py
spukhafte/cdce9xx.py
spukhafte/bin/__init__.py
spukhafte/bin/config.py
spukhafte_cdce9xx-0.9.1.dist-info/LICENSE
spukhafte_cdce9xx-0.9.1.dist-info/METADATA
spukhafte_cdce9xx-0.9.1.dist-info/WHEEL
spukhafte_cdce9xx-0.9.1.dist-info/entry_points.txt
spukhafte_cdce9xx-0.9.1.dist-info/top_level.txt
spukhafte_cdce9xx-0.9.1.dist-info/RECORD
