Metadata-Version: 2.1
Name: spukhafte-cdce9xx
Version: 0.9.1
Summary: Python3 I2C Driver & Application for TI CDCE9XX Clock Generators
Home-page: https://github.com/spukhafte-sys/cdce9xx
Author: Spukhafte Systems Limited
Author-email: fff@spukhafte.net
License: MIT
Project-URL: Bug Reports, https://github.com/spukhafte-sys/cdce9xx/issues
Project-URL: Source, https://github.com/spukhafte-sys/cdce9xx/
Keywords: i2c,cdce913,cdcel913,cdce925,cdcel925,cdce937,cdcel937,phase lock loop
Classifier: Development Status :: 4 - Beta
Classifier: Intended Audience :: Developers
Classifier: Topic :: Software Development :: Build Tools
Classifier: License :: OSI Approved :: MIT License
Classifier: Programming Language :: Python :: 3
Classifier: Programming Language :: Python :: 3.7
Classifier: Programming Language :: Python :: 3.8
Classifier: Programming Language :: Python :: 3.9
Classifier: Programming Language :: Python :: 3.10
Classifier: Programming Language :: Python :: 3 :: Only
Requires-Python: >=3.7.3, <4
License-File: LICENSE
Requires-Dist: smbus (>=1.1)
Requires-Dist: Adafruit-PlatformDetect (>=3.19.4)
